Metadata-Version: 2.1
Name: socialscore
Version: 2.1
Summary: Calculate the score of a social media profile and posts on twitter and other social media sites on the internet
Home-page: https://github.com/mr-ravin/social_score
Author: Ravin Kumar
Author-email: mr.ravin_kumar@hotmail.com
License: UNKNOWN
Keywords: Social Score,Social Media,Network,Social Network
Platform: UNKNOWN
Classifier: Programming Language :: Python :: 3
Classifier: License :: OSI Approved :: MIT License
Classifier: Operating System :: OS Independent
